authomize/rest_api_client/__init__.py
authomize/rest_api_client/client/__init__.py
authomize/rest_api_client/client/base_client.py
authomize/rest_api_client/client/client.py
authomize/rest_api_client/generated/__init__.py
authomize/rest_api_client/generated/schemas.py
authomize_rest_api_client-0.0.8.dist-info/LICENSE.txt
authomize_rest_api_client-0.0.8.dist-info/METADATA
authomize_rest_api_client-0.0.8.dist-info/WHEEL
authomize_rest_api_client-0.0.8.dist-info/top_level.txt
authomize_rest_api_client-0.0.8.dist-info/RECORD
